benito/__init__.py
benito/benny.py
benito/cli.py
benito/helpers.py
benito/py.typed
benny/__init__.py
benny/benny.py
benny/cli.py
benny/py.typed
benny/serial.py
emmet/cli.py
emmet/emmet.py
emmet/py.typed
gole/__init__.py
gole/benny.py
gole/cli.py
gole/helpers.py
gole/py.typed
robrick/__init__.py
robrick/benny.py
robrick/cli.py
robrick/helpers.py
robrick/py.typed
tegl/__init__.py
tegl/benny.py
tegl/cli.py
tegl/helpers.py
tegl/py.typed
robrick-0.0.0.dist-info/METADATA
robrick-0.0.0.dist-info/WHEEL
robrick-0.0.0.dist-info/entry_points.txt
robrick-0.0.0.dist-info/top_level.txt
robrick-0.0.0.dist-info/RECORD
