Metadata-Version: 2.1
Name: robrick
Version: 0.0.0
Summary: LEGO Robot Inventor helpers.
Home-page: https://github.com/eillarra/robrick
Author: eillarra
Author-email: eneko@illarra.com
License: MIT
Keywords: lego robot inventor mindstorms robotics ri5
Platform: UNKNOWN
Classifier: Development Status :: 1 - Planning
Classifier: Intended Audience :: Developers
Classifier: License :: OSI Approved :: MIT License
Classifier: Operating System :: OS Independent
Classifier: Programming Language :: Python
Classifier: Programming Language :: Python :: 3
Classifier: Programming Language :: Python :: 3.6
Classifier: Programming Language :: Python :: 3.7
Classifier: Programming Language :: Python :: 3.8
Classifier: Programming Language :: Python :: 3.9
Classifier: Programming Language :: Python :: 3.10
Classifier: Topic :: Utilities
Requires-Python: >=3.6
Requires-Dist: click
Requires-Dist: mpy-cross
Requires-Dist: mpy-repl-tool
Requires-Dist: pyserial
Requires-Dist: typing-extensions ; python_version < "3.8"
